{
  "_WARNING": "DRAFT — auto-generated by `cargo xtask extract-pdf`. Requires human review before promotion to a production profile.",
  "message_type": "MSCONS",
  "release": "2.4c",
  "segments": [
    {
      "level": 0,
      "mandatory": true,
      "max_occurrences": 1,
      "name": "Nutzdaten-Kopfsegment",
      "tag": "UNB"
    },
    {
      "level": 0,
      "mandatory": true,
      "max_occurrences": 1,
      "name": "Nachrichtenkopfsegment",
      "tag": "UNH"
    },
    {
      "level": 0,
      "mandatory": true,
      "max_occurrences": 1,
      "name": "Beginn der Nachricht",
      "tag": "BGM"
    },
    {
      "level": 1,
      "mandatory": true,
      "max_occurrences": 1,
      "name": "Nachrichtendatum",
      "tag": "DTM"
    },
    {
      "group": "SG1",
      "level": 1,
      "mandatory": true,
      "max_occurrences": 1,
      "name": "Referenz"
    },
    {
      "level": 1,
      "mandatory": true,
      "max_occurrences": 1,
      "name": "Referenzangaben",
      "tag": "RFF"
    },
    {
      "level": 2,
      "mandatory": false,
      "max_occurrences": 1,
      "name": "Versionsangabe marktlokationsscharfe",
      "tag": "DTM"
    },
    {
      "group": "SG2",
      "level": 1,
      "mandatory": true,
      "max_occurrences": 1,
      "name": "MP-ID Absender"
    },
    {
      "level": 1,
      "mandatory": true,
      "max_occurrences": 1,
      "name": "MP-ID Absender",
      "tag": "NAD"
    },
    {
      "group": "SG4",
      "level": 2,
      "mandatory": false,
      "max_occurrences": 1,
      "name": "Kontaktinformation"
    },
    {
      "level": 2,
      "mandatory": true,
      "max_occurrences": 1,
      "name": "Ansprechpartner",
      "tag": "CTA"
    },
    {
      "level": 3,
      "mandatory": true,
      "max_occurrences": 5,
      "name": "Kommunikationsverbindung",
      "tag": "COM"
    },
    {
      "level": 0,
      "mandatory": true,
      "max_occurrences": 1,
      "name": "Abschnitts-Kontrollsegment",
      "tag": "UNS"
    },
    {
      "group": "SG5",
      "level": 1,
      "mandatory": true,
      "max_occurrences": 99999,
      "name": "Liefer-, bzw. Bezugsort"
    },
    {
      "group": "SG6",
      "level": 2,
      "mandatory": true,
      "max_occurrences": 1,
      "name": "Bilanzkreis"
    },
    {
      "level": 2,
      "mandatory": true,
      "max_occurrences": 1,
      "name": "Bilanzkreis",
      "tag": "LOC"
    },
    {
      "level": 3,
      "mandatory": false,
      "max_occurrences": 1,
      "name": "Beginn Messperiode Übertragungszeitraum",
      "tag": "DTM"
    },
    {
      "group": "SG7",
      "level": 3,
      "mandatory": false,
      "max_occurrences": 1,
      "name": "Referenzangaben"
    },
    {
      "level": 3,
      "mandatory": true,
      "max_occurrences": 1,
      "name": "Gerätenummer",
      "tag": "RFF"
    },
    {
      "group": "SG8",
      "level": 3,
      "mandatory": false,
      "max_occurrences": 1,
      "name": "Zeitreihentyp"
    },
    {
      "level": 3,
      "mandatory": true,
      "max_occurrences": 1,
      "name": "Zeitreihentyp",
      "tag": "CCI"
    },
    {
      "group": "SG9",
      "level": 3,
      "mandatory": false,
      "max_occurrences": 99999,
      "name": "Positionsdaten"
    },
    {
      "level": 3,
      "mandatory": true,
      "max_occurrences": 1,
      "name": "lfd. Position",
      "tag": "LIN"
    },
    {
      "level": 4,
      "mandatory": true,
      "max_occurrences": 1,
      "name": "Produktidentifikation",
      "tag": "PIA"
    },
    {
      "group": "SG10",
      "level": 4,
      "mandatory": true,
      "max_occurrences": 9999,
      "name": "Mengen- und Statusangaben"
    },
    {
      "level": 4,
      "mandatory": true,
      "max_occurrences": 1,
      "name": "Mengenangaben",
      "tag": "QTY"
    },
    {
      "level": 5,
      "mandatory": false,
      "max_occurrences": 1,
      "name": "Beginn Messperiode",
      "tag": "DTM"
    },
    {
      "level": 5,
      "mandatory": false,
      "max_occurrences": 4,
      "name": "Plausibilisierungshinweis",
      "tag": "STS"
    },
    {
      "level": 0,
      "mandatory": true,
      "max_occurrences": 1,
      "name": "Nachrichten-Endesegment",
      "tag": "UNT"
    },
    {
      "level": 0,
      "mandatory": true,
      "max_occurrences": 1,
      "name": "Nutzdaten-Endesegment",
      "tag": "UNZ"
    }
  ],
  "source": "pdf-extract (EDI@Energy table parser)"
}