{
  "_comment": "BDEW EDI@Energy — EDIFACT message-type version metadata. Sources: https://www.bdew-mako.de/api/documents and https://www.bdew-mako.de/documents. Retrieved 2026-06-17. Each entry covers one (message_type, fv_version) pair. wire_release_code is the token that appears in UNH+2:2 of an inbound message; it must match mig.json 'release' for the profile to be found.",
  "profiles": [
    {
      "message_type": "UTILMD",
      "track": "Strom",
      "fv_version": "FV2024-10-01",
      "ahb_version": "1.2a",
      "mig_version": "S1.1a",
      "wire_release_code": "S1.1a",
      "valid_from": "2024-04-03",
      "valid_to": "2025-06-05",
      "profile_dir": "utilmd/fv20241001",
      "profile_release": "G1.0a",
      "release_match": true,
      "note": "Gas wire code G1.0a (AHB Gas 1.0a / MIG G1.0a) valid 2023-12-12 through 2026-03-31. Profile release matches."
    },
    {
      "message_type": "UTILMD",
      "track": "Strom",
      "fv_version": "FV2025-10-01",
      "ahb_version": "2.1",
      "mig_version": "S2.1",
      "wire_release_code": "S2.1",
      "valid_from": "2025-06-06",
      "valid_to": "2026-09-30",
      "profile_dir": "utilmd/fv20251001",
      "profile_release": "S2.1",
      "release_match": true,
      "note": "AHB Strom 2.1 / MIG S2.1 introduced per BK6-22-024 LFW25 on 2025-06-06, valid through FV2025-10-01 window end 2026-09-30. Latest consolidated: AHB Stand 27.03.2026, MIG Stand 02.03.2026. Profile release matches."
    },
    {
      "message_type": "UTILMD",
      "track": "Strom",
      "fv_version": "FV2026-10-01",
      "ahb_version": "2.2",
      "mig_version": "S2.2",
      "wire_release_code": "S2.2",
      "valid_from": "2026-10-01",
      "valid_to": null,
      "profile_dir": "utilmd/fv20261001",
      "profile_release": "S2.2",
      "release_match": true,
      "note": "Next annual window. AHB Strom 2.2 / MIG S2.2 (Konsultation Feb 2026, final released). Profile release matches."
    },
    {
      "message_type": "UTILMD",
      "track": "Gas",
      "fv_version": "FV2024-10-01",
      "ahb_version": "1.0a",
      "mig_version": "G1.0a",
      "wire_release_code": "G1.0a",
      "valid_from": "2023-12-12",
      "valid_to": "2026-03-31",
      "profile_dir": "utilmd/fv20241001_gas",
      "profile_release": "G1.0a",
      "release_match": true,
      "note": "Gas wire code G1.0a (AHB Gas 1.0a / MIG G1.0a) valid 2023-12-12 through 2026-03-31. Profile release matches."
    },
    {
      "message_type": "UTILMD",
      "track": "Gas",
      "fv_version": "FV2025-10-01",
      "ahb_version": "1.1",
      "mig_version": "G1.1",
      "wire_release_code": "G1.1",
      "valid_from": "2026-04-01",
      "valid_to": "2026-09-30",
      "profile_dir": "utilmd/fv20251001_gas",
      "profile_release": "G1.1",
      "release_match": true,
      "note": "AHB Gas 1.1 / MIG G1.1 introduced 2026-04-01, within the FV2025-10-01 window. Currently active (2026-06-17). Latest consolidated: AHB Stand 27.03.2026. Profile release matches."
    },
    {
      "message_type": "UTILMD",
      "track": "Gas",
      "fv_version": "FV2026-10-01",
      "ahb_version": "1.2",
      "mig_version": "G1.2",
      "wire_release_code": "G1.2",
      "valid_from": "2026-10-01",
      "valid_to": null,
      "profile_dir": "utilmd/fv20261001_gas",
      "profile_release": "G1.2",
      "release_match": true,
      "note": "Next annual window. AHB Gas 1.2 / MIG G1.2. Profile release matches."
    },
    {
      "message_type": "APERAK",
      "track": null,
      "fv_version": "FV2025-10-01",
      "ahb_version": "1.0",
      "mig_version": "2.1i",
      "wire_release_code": "2.1i",
      "valid_from": "2025-10-01",
      "valid_to": "2026-09-30",
      "profile_dir": "aperak/fv20251001",
      "profile_release": "2.1i",
      "release_match": true,
      "note": "APERAK AHB 1.0 / MIG 2.1i. Profile release matches."
    },
    {
      "message_type": "APERAK",
      "track": null,
      "fv_version": "FV2026-10-01",
      "ahb_version": "1.1",
      "mig_version": "2.2",
      "wire_release_code": "2.2",
      "valid_from": "2026-10-01",
      "valid_to": null,
      "profile_dir": "aperak/fv20261001",
      "profile_release": "2.2",
      "release_match": true,
      "note": "Next annual window. APERAK AHB 1.1 / MIG 2.2. Profile release matches."
    },
    {
      "message_type": "COMDIS",
      "track": null,
      "fv_version": "FV2025-10-01",
      "ahb_version": "1.0g",
      "mig_version": "1.0f",
      "wire_release_code": "1.0f",
      "valid_from": "2025-10-01",
      "valid_to": "2026-03-31",
      "profile_dir": "comdis/fv20251001",
      "profile_release": "1.0f",
      "release_match": true,
      "note": "COMDIS AHB 1.0g / MIG 1.0f. Valid to 2026-03-31; COMDIS AHB 1.0h (MIG 1.0h) takes over from 2026-04-01."
    },
    {
      "message_type": "COMDIS",
      "track": null,
      "fv_version": "FV2026-10-01",
      "ahb_version": "1.0h",
      "mig_version": "1.0h",
      "wire_release_code": "1.0h",
      "valid_from": "2026-04-01",
      "valid_to": null,
      "profile_dir": "comdis/fv20261001",
      "profile_release": "1.0h",
      "release_match": true,
      "note": "COMDIS AHB 1.0h / MIG 1.0h introduced 2026-04-01. Profile release matches wire code."
    },
    {
      "message_type": "CONTRL",
      "track": null,
      "fv_version": "FV2025-10-01",
      "ahb_version": "1.0",
      "mig_version": "2.0b",
      "wire_release_code": "2.0b",
      "valid_from": "2025-10-01",
      "valid_to": null,
      "profile_dir": "contrl/fv20251001",
      "profile_release": "2.0b",
      "release_match": true,
      "note": "CONTRL AHB 1.0. Open-ended validity. Profile release matches."
    },
    {
      "message_type": "CONTRL",
      "track": null,
      "fv_version": "FV2026-01-01",
      "ahb_version": "1.0",
      "mig_version": "2.0b",
      "wire_release_code": "2.0b",
      "valid_from": "2026-01-01",
      "valid_to": null,
      "profile_dir": "contrl/fv20260101",
      "profile_release": "2.0b",
      "release_match": true,
      "note": "Duplicate profile for CONTRL in FV2026-01-01 directory. Same MIG version 2.0b."
    },
    {
      "message_type": "IFTSTA",
      "track": null,
      "fv_version": "FV2025-10-01",
      "ahb_version": "2.0h",
      "mig_version": "2.0g",
      "wire_release_code": "2.0g",
      "valid_from": "2025-10-01",
      "valid_to": "2026-09-30",
      "profile_dir": "iftsta/fv20251001",
      "profile_release": "2.0g",
      "release_match": true,
      "note": "IFTSTA AHB 2.0h / MIG 2.0g. Latest consolidated AHB: Stand 23.06.2025. Profile release matches."
    },
    {
      "message_type": "IFTSTA",
      "track": null,
      "fv_version": "FV2026-10-01",
      "ahb_version": "2.1",
      "mig_version": null,
      "wire_release_code": "2.1",
      "valid_from": "2026-10-01",
      "valid_to": null,
      "profile_dir": "iftsta/fv20261001",
      "profile_release": "2.1",
      "release_match": true,
      "note": "Next annual window. IFTSTA AHB 2.1. Profile release matches."
    },
    {
      "message_type": "INSRPT",
      "track": null,
      "fv_version": "FV2021-10-01",
      "ahb_version": "1.1g",
      "mig_version": "1.1a",
      "wire_release_code": "1.1a",
      "valid_from": "2021-10-01",
      "valid_to": null,
      "profile_dir": "insrpt/fv20211001",
      "profile_release": "1.1a",
      "release_match": true,
      "note": "INSRPT AHB 1.1g / MIG 1.1a. Open-ended (still valid 2026-06-17). Profile release matches."
    },
    {
      "message_type": "INSRPT",
      "track": null,
      "fv_version": "FV2026-01-01",
      "ahb_version": "1.1g",
      "mig_version": "1.1a",
      "wire_release_code": "1.1a",
      "valid_from": "2026-01-01",
      "valid_to": null,
      "profile_dir": "insrpt/fv20260101",
      "profile_release": "1.1a",
      "release_match": true,
      "note": "Duplicate profile for INSRPT in FV2026-01-01 directory. Same release."
    },
    {
      "message_type": "INVOIC",
      "track": null,
      "fv_version": "FV2025-10-01",
      "ahb_version": "1.0",
      "mig_version": "2.8e",
      "wire_release_code": "2.8e",
      "valid_from": "2025-10-01",
      "valid_to": "2026-03-31",
      "profile_dir": "invoic/fv20251001",
      "profile_release": "2.8e",
      "release_match": true,
      "note": "INVOIC AHB 1.0 / MIG 2.8e. Valid to 2026-03-31 per BDEW schedule. Profile release matches."
    },
    {
      "message_type": "INVOIC",
      "track": null,
      "fv_version": "FV2026-04-01",
      "ahb_version": "1.0",
      "mig_version": "2.8e",
      "wire_release_code": "2.8e",
      "valid_from": "2026-04-01",
      "valid_to": null,
      "profile_dir": "invoic/fv20260401",
      "profile_release": "2.8e",
      "release_match": true,
      "note": "INVOIC continues with MIG 2.8e from 2026-04-01. Profile release matches."
    },
    {
      "message_type": "MSCONS",
      "track": null,
      "fv_version": "FV2024-04-01",
      "ahb_version": "3.1d",
      "mig_version": "2.4c",
      "wire_release_code": "2.4c",
      "valid_from": "2024-04-01",
      "valid_to": "2025-10-01",
      "profile_dir": "mscons/fv20240401",
      "profile_release": "2.4c",
      "release_match": true,
      "note": "MSCONS AHB 3.1d / MIG 2.4c (valid until FV2025-10-01 cutover). Profile release matches."
    },
    {
      "message_type": "MSCONS",
      "track": null,
      "fv_version": "FV2025-10-01",
      "ahb_version": "3.1d",
      "mig_version": "2.4c",
      "wire_release_code": "2.4c",
      "valid_from": "2025-10-01",
      "valid_to": "2026-09-30",
      "profile_dir": "mscons/fv20251001",
      "profile_release": "2.4c",
      "release_match": true,
      "note": "MSCONS AHB 3.1d / MIG 2.4c continues in FV2025-10-01 window. MSCONS AHB 3.2 / MIG 2.5 was in consultation Feb 2026 for the next window. Profile release matches."
    },
    {
      "message_type": "MSCONS",
      "track": null,
      "fv_version": "FV2026-10-01",
      "ahb_version": "3.2",
      "mig_version": "2.5",
      "wire_release_code": "2.5",
      "valid_from": "2026-10-01",
      "valid_to": null,
      "profile_dir": "mscons/fv20261001",
      "profile_release": "2.5",
      "release_match": true,
      "note": "Next annual window. MSCONS AHB 3.2 / MIG 2.5 (Konsultation Feb 2026). Profile release matches."
    },
    {
      "message_type": "ORDCHG",
      "track": null,
      "fv_version": "FV2024-10-01",
      "ahb_version": "1.0a",
      "mig_version": "1.1",
      "wire_release_code": "1.1",
      "valid_from": "2024-10-01",
      "valid_to": "2026-03-31",
      "profile_dir": "ordchg/fv20241001",
      "profile_release": "1.1",
      "release_match": true,
      "note": "ORDCHG AHB 1.0a / MIG 1.1. Valid until ORDCHG 1.2 introduced 2026-04-01. Profile release matches."
    },
    {
      "message_type": "ORDCHG",
      "track": null,
      "fv_version": "FV2026-04-01",
      "ahb_version": "1.1",
      "mig_version": "1.2",
      "wire_release_code": "1.2",
      "valid_from": "2026-04-01",
      "valid_to": null,
      "profile_dir": "ordchg/fv20260401",
      "profile_release": "1.2",
      "release_match": true,
      "note": "ORDCHG AHB 1.1 / MIG 1.2 from 2026-04-01. Currently active (2026-06-17). Profile release matches."
    },
    {
      "message_type": "ORDERS",
      "track": null,
      "fv_version": "FV2025-10-01",
      "ahb_version": "1.1",
      "mig_version": "1.4b",
      "wire_release_code": "1.4b",
      "valid_from": "2025-10-01",
      "valid_to": "2026-03-31",
      "profile_dir": "orders/fv20251001",
      "profile_release": "1.4b",
      "release_match": true,
      "note": "ORDERS AHB 1.1 / MIG 1.4b. Valid until 2026-03-31. Profile release matches."
    },
    {
      "message_type": "ORDERS",
      "track": null,
      "fv_version": "FV2026-04-01",
      "ahb_version": "1.1",
      "mig_version": "1.4b",
      "wire_release_code": "1.4b",
      "valid_from": "2026-04-01",
      "valid_to": null,
      "profile_dir": "orders/fv20260401",
      "profile_release": "1.4b",
      "release_match": true,
      "note": "ORDERS continues with MIG 1.4b from 2026-04-01. Currently active (2026-06-17). Profile release matches."
    },
    {
      "message_type": "ORDRSP",
      "track": null,
      "fv_version": "FV2025-10-01",
      "ahb_version": "1.1",
      "mig_version": "1.4a",
      "wire_release_code": "1.4a",
      "valid_from": "2025-10-01",
      "valid_to": "2026-03-31",
      "profile_dir": "ordrsp/fv20251001",
      "profile_release": "1.4a",
      "release_match": true,
      "note": "ORDRSP AHB 1.1 / MIG 1.4a. Valid until 2026-03-31. Profile release matches."
    },
    {
      "message_type": "ORDRSP",
      "track": null,
      "fv_version": "FV2026-04-01",
      "ahb_version": "1.1",
      "mig_version": "1.4b",
      "wire_release_code": "1.4b",
      "valid_from": "2026-04-01",
      "valid_to": null,
      "profile_dir": "ordrsp/fv20260401",
      "profile_release": "1.4b",
      "release_match": true,
      "note": "ORDRSP AHB 1.1 / MIG 1.4b from 2026-04-01. Currently active (2026-06-17). Profile release matches."
    },
    {
      "message_type": "PARTIN",
      "track": null,
      "fv_version": "FV2025-10-01",
      "ahb_version": "1.0e",
      "mig_version": "1.0f",
      "wire_release_code": "1.0f",
      "valid_from": "2025-10-01",
      "valid_to": "2026-03-31",
      "profile_dir": "partin/fv20251001",
      "profile_release": "1.0f",
      "release_match": true,
      "note": "PARTIN AHB 1.0e / MIG 1.0f. Valid until PARTIN 1.1 introduced 2026-04-01. Profile release matches."
    },
    {
      "message_type": "PARTIN",
      "track": null,
      "fv_version": "FV2026-04-01",
      "ahb_version": "1.1",
      "mig_version": "1.1",
      "wire_release_code": "1.1",
      "valid_from": "2026-04-01",
      "valid_to": null,
      "profile_dir": "partin/fv20260401",
      "profile_release": "1.1",
      "release_match": true,
      "note": "PARTIN AHB 1.1 / MIG 1.1 from 2026-04-01. Currently active (2026-06-17). Profile release matches."
    },
    {
      "message_type": "PRICAT",
      "track": null,
      "fv_version": "FV2025-04-01",
      "ahb_version": "2.0f",
      "mig_version": "2.0e",
      "wire_release_code": "2.0e",
      "valid_from": "2025-04-01",
      "valid_to": "2026-03-31",
      "profile_dir": "pricat/fv20250401",
      "profile_release": "2.0e",
      "release_match": true,
      "note": "PRICAT AHB 2.0f / MIG 2.0e. Latest consolidated AHB Stand 11.12.2025 valid to 2026-09-30. Profile release matches."
    },
    {
      "message_type": "PRICAT",
      "track": null,
      "fv_version": "FV2026-04-01",
      "ahb_version": "2.0f",
      "mig_version": "2.0e",
      "wire_release_code": "2.0e",
      "valid_from": "2026-04-01",
      "valid_to": null,
      "profile_dir": "pricat/fv20260401",
      "profile_release": "2.0e",
      "release_match": true,
      "note": "PRICAT continues with same MIG 2.0e in FV2026-04-01 directory. Profile release matches."
    },
    {
      "message_type": "QUOTES",
      "track": null,
      "fv_version": "FV2025-04-01",
      "ahb_version": "1.0",
      "mig_version": "1.3b",
      "wire_release_code": "1.3b",
      "valid_from": "2025-04-01",
      "valid_to": "2026-01-29",
      "profile_dir": "quotes/fv20250401",
      "profile_release": "1.3b",
      "release_match": true,
      "note": "QUOTES AHB 1.0 / MIG 1.3b. QUOTES MIG 1.3b consolidated Stand 30.01.2026 — superseded by 1.3c from 2026-01-30. Profile release matches."
    },
    {
      "message_type": "QUOTES",
      "track": null,
      "fv_version": "FV2026-04-01",
      "ahb_version": "1.0",
      "mig_version": "1.3c",
      "wire_release_code": "1.3c",
      "valid_from": "2026-04-01",
      "valid_to": null,
      "profile_dir": "quotes/fv20260401",
      "profile_release": "1.3c",
      "release_match": true,
      "note": "QUOTES MIG 1.3c from 2026-04-01. Currently active (2026-06-17). Profile release matches."
    },
    {
      "message_type": "REMADV",
      "track": null,
      "fv_version": "FV2025-10-01",
      "ahb_version": "1.0",
      "mig_version": "2.9d",
      "wire_release_code": "2.9d",
      "valid_from": "2025-10-01",
      "valid_to": "2026-03-31",
      "profile_dir": "remadv/fv20251001",
      "profile_release": "2.9d",
      "release_match": true,
      "note": "REMADV AHB 1.0 / MIG 2.9d. Valid to 2026-03-31. Profile release matches."
    },
    {
      "message_type": "REMADV",
      "track": null,
      "fv_version": "FV2026-04-01",
      "ahb_version": "1.0",
      "mig_version": "2.9e",
      "wire_release_code": "2.9e",
      "valid_from": "2026-04-01",
      "valid_to": null,
      "profile_dir": "remadv/fv20260401",
      "profile_release": "2.9e",
      "release_match": true,
      "note": "REMADV AHB 1.0 / MIG 2.9e from 2026-04-01. Currently active (2026-06-17). Profile release matches."
    },
    {
      "message_type": "REQOTE",
      "track": null,
      "fv_version": "FV2025-04-01",
      "ahb_version": "1.0a",
      "mig_version": "1.3c",
      "wire_release_code": "1.3c",
      "valid_from": "2025-04-01",
      "valid_to": "2026-03-31",
      "profile_dir": "reqote/fv20250401",
      "profile_release": "1.3c",
      "release_match": true,
      "note": "REQOTE AHB 1.0a / MIG 1.3c. Profile release matches."
    },
    {
      "message_type": "REQOTE",
      "track": null,
      "fv_version": "FV2026-04-01",
      "ahb_version": "1.0a",
      "mig_version": "1.3c",
      "wire_release_code": "1.3c",
      "valid_from": "2026-04-01",
      "valid_to": null,
      "profile_dir": "reqote/fv20260401",
      "profile_release": "1.3c",
      "release_match": true,
      "note": "REQOTE continues with same MIG 1.3c. Profile release matches."
    },
    {
      "message_type": "UTILTS",
      "track": null,
      "fv_version": "FV2024-10-01",
      "ahb_version": "1.0",
      "mig_version": "1.1c",
      "wire_release_code": "1.1c",
      "valid_from": "2024-10-01",
      "valid_to": "2026-03-31",
      "profile_dir": "utilts/fv20241001",
      "profile_release": "1.1c",
      "release_match": true,
      "note": "UTILTS AHB 1.0 / MIG 1.1c for FV2024-10-01 window. Valid to 2026-03-31. Profile release matches."
    },
    {
      "message_type": "UTILTS",
      "track": null,
      "fv_version": "FV2026-04-01",
      "ahb_version": "1.0",
      "mig_version": "1.1e",
      "wire_release_code": "1.1e",
      "valid_from": "2026-04-01",
      "valid_to": null,
      "profile_dir": "utilts/fv20260401",
      "profile_release": "1.1e",
      "release_match": true,
      "note": "UTILTS AHB 1.0 / MIG 1.1e from 2026-04-01. Currently active (2026-06-17). Profile release matches."
    }
  ],
  "release_mismatches": [
    {
      "profile_dir": "utilmd/fv20241001",
      "profile_release": "S2.1",
      "bdew_wire_code": "S1.1a",
      "severity": "Critical",
      "impact": "UTILMD Strom messages from FV2024-10-01 window (Oct 2024 – Jun 2025) arrive with wire code S1.1a; fv20241001 profile has release S2.1. No profile matches → ProfileNotFound for all Strom messages in this historical window."
    },
    {
      "profile_dir": "utilmd/fv20241001_gas",
      "profile_release": "G1.1",
      "bdew_wire_code": "G1.0a",
      "severity": "Critical",
      "impact": "UTILMD Gas messages from FV2024-10-01 window (Oct 2024 – Mar 2026) arrive with wire code G1.0a; fv20241001_gas profile has release G1.1. No profile matches → ProfileNotFound for all Gas messages in the FV2024-10-01 window and first half of FV2025-10-01 window."
    }
  ]
}
